MANIFEST.in
README.md
setup.py
torpc/__init__.py
torpc/rpc.py
torpc/services.py
torpc/tcp.py
torpc/util.py
torpc.egg-info/PKG-INFO
torpc.egg-info/SOURCES.txt
torpc.egg-info/dependency_links.txt
torpc.egg-info/top_level.txt