Metadata-Version: 1.0
Name: torpc
Version: 0.0.1
Summary: A tiny async tcp and duplex rpc implementation using Tornado IOLoop.
Home-page: http://github.com/yoki123/torpc
Author: Yoki
Author-email: ispeedly@gmail.com
License: MIT
Keywords: tornado,rpc,async
Platform: UNKNOWN
